{
  "servidores": [
    {
      "nome": "BATISTA BRASÍLIA",
      "ip": "100.82.231.54",
      "rede": "privada"
    },
    {
      "nome": "BATISTA BRASILEIRO (SP)",
      "ip": "100.78.45.19",
      "rede": "privada"
    },
    {
      "nome": "COC LAGO NORTE",
      "ip": "100.118.5.33",
      "rede": "privada"
    },
    {
      "nome": "CCI",
      "ip": "100.65.138.1",
      "rede": "privada",
      "usuario": "ASA SUL"
    },
    {
      "nome": "BATISTA PALMAS",
      "ip": "100.78.178.114",
      "rede": "privada",
      "usuario": "Biomessenger"
    },
    {
      "nome": "GALOIS",
      "ip": "100.67.3.97",
      "rede": "privada",
      "usuario": "BIomessenger"
    },
    {
      "nome": "GALOIS LE PETIT",
      "ip": "100.124.102.26",
      "rede": "privada",
      "usuario": "SERVIDOR BIO"
    }
  ]
}